oepandas/__init__.py
oepandas/exception.py
oepandas/pandas.pyi
oepandas/pandas_extensions.py
oepandas/py.typed
oepandas/util.py
oepandas/arrays/__init__.py
oepandas/arrays/base.py
oepandas/arrays/design_unit.py
oepandas/arrays/display.py
oepandas/arrays/molecule.py
oepandas-2.0.1.dist-info/licenses/LICENSE
oepandas-2.0.1.dist-info/METADATA
oepandas-2.0.1.dist-info/WHEEL
oepandas-2.0.1.dist-info/top_level.txt
oepandas-2.0.1.dist-info/RECORD
