Metadata-Version: 2.4
Name: oepandas
Version: 2.0.1
Summary: Native handling of OpenEye objects in Pandas
Author-email: Scott Arne Johnson <scott.arne.johnson@gmail.com>
License-Expression: MIT
Keywords: science
Classifier: Development Status :: 5 - Production/Stable
Classifier: Programming Language :: Python :: 3 :: Only
Requires-Python: >=3.10
License-File: LICENSE
Requires-Dist: pandas>=2.1.0
Requires-Dist: numpy
Requires-Dist: openeye-toolkits>=2023.1.0
Requires-Dist: more-itertools
Provides-Extra: dev
Requires-Dist: invoke; extra == "dev"
Requires-Dist: build; extra == "dev"
Requires-Dist: pytest; extra == "dev"
Dynamic: license-file
